{
  "title": "20250617_174143.jpg",
   "description": "",
"color": [0, 0,  255, 50],
  "imageViews": "0",
  "creationTime": {
    "timestamp": "1753102440",
    "formatted": "2025/07/21 12:54:00 UTC"
  },
  "photoTakenTime": {
    "timestamp": "1750149704",
    "formatted": "2025/06/17 8:41:44 UTC"
  },
  "geoData": {
    "latitude": 34.7122536,
    "longitude": 137.6879883,
    "altitude": 42.0,
    "latitudeSpan": 0.0,
    "longitudeSpan": 0.0
  },
  "geoDataExif": {
    "latitude": 34.7122536,
    "longitude": 137.6879883,
    "altitude": 42.0,
    "latitudeSpan": 0.0,
    "longitudeSpan": 0.0
  },
  "url": "https://photos.google.com/photo/AF1QipPJ8hJsNYrIOhl1_uW-HldOlba7OCfyhoiHJq-i",
  "googlePhotosOrigin": {
    "mobileUpload": {
      "deviceFolder": {
        "localFolderName": ""
      },
      "deviceType": "ANDROID_PHONE"
    }
  }
}