{
  "title": "20250426_135951.jpg",
   "description": "",
"color": [0, 0,  255, 50],
  "imageViews": "2",
  "creationTime": {
    "timestamp": "1753102440",
    "formatted": "2025/07/21 12:54:00 UTC"
  },
  "photoTakenTime": {
    "timestamp": "1745643591",
    "formatted": "2025/04/26 4:59:51 UTC"
  },
  "geoData": {
    "latitude": 34.7077141,
    "longitude": 137.6919556,
    "altitude": 78.0,
    "latitudeSpan": 0.0,
    "longitudeSpan": 0.0
  },
  "geoDataExif": {
    "latitude": 34.7077141,
    "longitude": 137.6919556,
    "altitude": 78.0,
    "latitudeSpan": 0.0,
    "longitudeSpan": 0.0
  },
  "url": "https://photos.google.com/photo/AF1QipOJznG6Gzq8uDvmK_nAtX1f8Qey-JaGiuo8IfJx",
  "googlePhotosOrigin": {
    "mobileUpload": {
      "deviceFolder": {
        "localFolderName": ""
      },
      "deviceType": "ANDROID_PHONE"
    }
  }
}